huemans/__init__.py
huemans/bridge.py
huemans/group.py
huemans/light.py
huemans/sensor.py
huemans/utils/__init__.py
huemans/utils/condition.py
huemans/utils/time_pattern.py
huemans-0.1.dist-info/DESCRIPTION.rst
huemans-0.1.dist-info/METADATA
huemans-0.1.dist-info/RECORD
huemans-0.1.dist-info/WHEEL
huemans-0.1.dist-info/metadata.json
huemans-0.1.dist-info/top_level.txt
