Metadata-Version: 2.0
Name: huemans
Version: 0.1
Summary: Huemans, a Philips Hue API Python wrapper for huemans
Home-page: https://github.com/mikkogozalo/huemans
Author: Mikko Gozalo
Author-email: mikgozalo@gmail.com
License: MIT
Keywords: philips hue api
Platform: UNKNOWN
Classifier: Development Status :: 3 - Alpha
Classifier: Intended Audience :: Developers
Classifier: Topic :: Software Development :: Build Tools
Classifier: License :: OSI Approved :: MIT License
Classifier: Programming Language :: Python :: 3
Classifier: Programming Language :: Python :: 3.3
Classifier: Programming Language :: Python :: 3.4
Classifier: Programming Language :: Python :: 3.5
Classifier: Programming Language :: Python :: 3.6
Requires-Dist: requests
